dora_parser/__init__.py
dora_parser/__main__.py
dora_parser/dialects/__init__.py
dora_parser/dialects/athena.py
dora_parser/dialects/hive.py
dora_parser/dialects/impala.py
dora_parser/dialects/presto.py
dora_parser/dialects/spark.py
dora_parser/parser.py
dora_parser/reader.py
dora_parser/report.py
dora_parser/transpiler.py
dora_parser-0.1.3.dist-info/LICENSE
dora_parser-0.1.3.dist-info/WHEEL
dora_parser-0.1.3.dist-info/METADATA
dora_parser-0.1.3.dist-info/RECORD
