Metadata-Version: 2.1
Name: dora-parser
Version: 0.1.3
Summary: SQL Parser ans Transpiler
Home-page: https://github.com/doraproject/parser
License: Apache-2.0
Keywords: dora,sql,parser,impala,presto,hive,spark
Author: DataLabs
Author-email: time.dataanalytics.datalabs@compasso.com.br
Requires-Python: >=3.7.1,<4.0.0
Classifier: License :: OSI Approved :: Apache Software License
Classifier: Programming Language :: Python :: 3
Classifier: Programming Language :: Python :: 3.10
Classifier: Programming Language :: Python :: 3.8
Classifier: Programming Language :: Python :: 3.9
Provides-Extra: pandas
Provides-Extra: seaborn
Requires-Dist: fire (>=0.4.0,<0.5.0)
Requires-Dist: mo-sql-parsing (==5.43.21240)
Requires-Dist: pandas (>=1.3.0,<2.0.0); extra == "pandas"
Requires-Dist: seaborn (>=0.11.1,<0.12.0); extra == "seaborn"
Requires-Dist: sql-formatter (>=0.6.2,<0.7.0)
Project-URL: Repository, https://github.com/doraproject/parser.git
